Workbook

Sheet 前提
A1: 項目 | B1: 値 | C1: 根拠・扱い
A2: 時間原価 | B2: 5000 | C2: 既存モデルの仮定。実支払ではない
A3: 決済率 | B3: 0.03 | C3: 既存の仮定。決済手段別の実績未確認
A4: 目標案件貢献率 | B4: 0.5 | C4: 既存モデル。営業利益率ではない
A5: 月間時間 | B5: 140 | C5: 既存のユーザー指定
A6: 営業事務 | B6: 28 | C6: 仮定
A7: 予備時間 | B7: 28 | C7: 仮定
A8: 固定費 | B8: 50000 | C8: 内訳・実支払未確認
A9: 工数ストレス | B9: 1.25 | C9: 25%増の仮定
A10: 支援追加時間 | B10: 0.5 | C10: 1社あたり30分/月の仮定
A11: 顧客外部費月額 | B11: 3500 | C11: 公開の仮置き。実見積に置換
A12: 比較月数 | B12: 36 | C12: 顧客総額の期間
A13: 通常予約上限 | B13: =(B5-B6-B7)/B9 -> 67.2 | C13: 25%の工数増を吸収する目安。追加支援ストレスは別
A14: 読み方 | B14: 未採用案 | C14: 青文字・黄色セルが入力。黒文字は数式。新価格をサイトへ自動反映しない
A15: 境界 | B15: 税別円 | C15: 外部料金は出典の通貨・税込/税別を別記。余力は税引後利益ではない

Sheet 基本料金
A1: 商品 | B1: 状態 | C1: 現行価格 | D1: 現行時間h | E1: 現金費+獲得費 | F1: 現行貢献率 | G1: 50%維持の上限h | H1: 25%増時の最低価格 | I1: 改定検討価格 | J1: 検討時の時間h | K1: 検討価格の貢献率 | L1: 出所
A2: 入口をつくる | B2: 現行 | C2: 79800 | D2: 5.5 | E2: 8000 | F2: =IF(C2=0,0,(C2*(1-前提!$B$3)-D2*前提!$B$2-E2)/C2) -> 0.52513784 | G2: =(C2*(1-前提!$B$3-前提!$B$4)-E2)/前提!$B$2 -> 5.9012 | H2: =ROUNDUP((D2*前提!$B$9*前提!$B$2+E2)/(1-前提!$B$3-前提!$B$4),0) -> 90160 | I2: 99800 | J2: 6.875 | K2: =IF(I2=0,0,(I2*(1-前提!$B$3)-J2*前提!$B$2-E2)/I2) -> 0.5454008 | L2: proposal.json / 改定価格は今回の未採用提案
A3: 事業の土台をつくる | B3: 現行 | C3: 198000 | D3: 15 | E3: 15000 | F3: =IF(C3=0,0,(C3*(1-前提!$B$3)-D3*前提!$B$2-E3)/C3) -> 0.51545455 | G3: =(C3*(1-前提!$B$3-前提!$B$4)-E3)/前提!$B$2 -> 15.612 | H3: =ROUNDUP((D3*前提!$B$9*前提!$B$2+E3)/(1-前提!$B$3-前提!$B$4),0) -> 231383 | I3: 248000 | J3: 18.75 | K3: =IF(I3=0,0,(I3*(1-前提!$B$3)-J3*前提!$B$2-E3)/I3) -> 0.53149194 | L3: proposal.json / 改定価格は今回の未採用提案
A4: 情報を育てる | B4: 準備中 | C4: 398000 | D4: 26 | E4: 30000 | F4: =IF(C4=0,0,(C4*(1-前提!$B$3)-D4*前提!$B$2-E4)/C4) -> 0.56798995 | G4: =(C4*(1-前提!$B$3-前提!$B$4)-E4)/前提!$B$2 -> 31.412 | H4: =ROUNDUP((D4*前提!$B$9*前提!$B$2+E4)/(1-前提!$B$3-前提!$B$4),0) -> 409575 | I4: 448000 | J4: 32.5 | K4: =IF(I4=0,0,(I4*(1-前提!$B$3)-J4*前提!$B$2-E4)/I4) -> 0.5403125 | L4: proposal.json / 改定価格は今回の未採用提案
A5: 自分で管理 | B5: 現行 | C5: 0 | D5: 0 | E5: 0 | F5: =IF(C5=0,0,(C5*(1-前提!$B$3)-D5*前提!$B$2-E5)/C5) -> 0 | G5: =(C5*(1-前提!$B$3-前提!$B$4)-E5)/前提!$B$2 -> 0 | H5: =ROUNDUP((D5*前提!$B$9*前提!$B$2+E5)/(1-前提!$B$3-前提!$B$4),0) -> 0 | I5: 0 | J5: 0 | K5: =IF(I5=0,0,(I5*(1-前提!$B$3)-J5*前提!$B$2-E5)/I5) -> 0 | L5: proposal.json / 改定価格は今回の未採用提案
A6: 守る | B6: 提供条件確認が必要 | C6: 3900 | D6: 0.3 | E6: 300 | F6: =IF(C6=0,0,(C6*(1-前提!$B$3)-D6*前提!$B$2-E6)/C6) -> 0.50846154 | G6: =(C6*(1-前提!$B$3-前提!$B$4)-E6)/前提!$B$2 -> 0.3066 | H6: =ROUNDUP((D6*前提!$B$9*前提!$B$2+E6)/(1-前提!$B$3-前提!$B$4),0) -> 4628 | I6: 6900 | J6: 0.5 | K6: =IF(I6=0,0,(I6*(1-前提!$B$3)-J6*前提!$B$2-E6)/I6) -> 0.5642029 | L6: proposal.json / 改定価格は今回の未採用提案
A7: 整える | B7: 提供条件確認が必要 | C7: 9800 | D7: 0.75 | E7: 400 | F7: =IF(C7=0,0,(C7*(1-前提!$B$3)-D7*前提!$B$2-E7)/C7) -> 0.54653061 | G7: =(C7*(1-前提!$B$3-前提!$B$4)-E7)/前提!$B$2 -> 0.8412 | H7: =ROUNDUP((D7*前提!$B$9*前提!$B$2+E7)/(1-前提!$B$3-前提!$B$4),0) -> 10825 | I7: 12800 | J7: 1 | K7: =IF(I7=0,0,(I7*(1-前提!$B$3)-J7*前提!$B$2-E7)/I7) -> 0.548125 | L7: proposal.json / 改定価格は今回の未採用提案
A8: 育てる | B8: 提供条件確認が必要 | C8: 29800 | D8: 2.25 | E8: 700 | F8: =IF(C8=0,0,(C8*(1-前提!$B$3)-D8*前提!$B$2-E8)/C8) -> 0.56899329 | G8: =(C8*(1-前提!$B$3-前提!$B$4)-E8)/前提!$B$2 -> 2.6612 | H8: =ROUNDUP((D8*前提!$B$9*前提!$B$2+E8)/(1-前提!$B$3-前提!$B$4),0) -> 31410 | I8: 34800 | J8: 2.8125 | K8: =IF(I8=0,0,(I8*(1-前提!$B$3)-J8*前提!$B$2-E8)/I8) -> 0.54579023 | L8: proposal.json / 改定価格は今回の未採用提案

Sheet 追加と検討商品
A1: 商品 | B1: 現行/検討価格 | C1: 現金費の仮入力 | D1: 50%維持の最大時間h | E1: 判断 | F1: 根拠
A2: 追加ページ | B2: 33000 | C2: 0 | D2: =(B2*(1-前提!$B$3-前提!$B$4)-C2)/前提!$B$2 -> 3.102 | E2: 3.10h以内（現金費0の場合）。新規構成・原稿は別 | F2: prices.ts / PROPOSED_PRICES。現金費0は上限確認用であり実原価ではない
A3: 半日撮影 | B3: 55000 | C3: 0 | D3: =(B3*(1-前提!$B$3-前提!$B$4)-C3)/前提!$B$2 -> 5.17 | E3: 参考額維持。移動・編集・外注を個別積算 | F3: prices.ts / PROPOSED_PRICES。現金費0は上限確認用であり実原価ではない
A4: 1日撮影 | B4: 88000 | C4: 0 | D4: =(B4*(1-前提!$B$3-前提!$B$4)-C4)/前提!$B$2 -> 8.272 | E4: 参考額維持。現場だけでなく準備と編集を含む | F4: prices.ts / PROPOSED_PRICES。現金費0は上限確認用であり実原価ではない
A5: ロゴ | B5: 88000 | C5: 0 | D5: =(B5*(1-前提!$B$3-前提!$B$4)-C5)/前提!$B$2 -> 8.272 | E5: 提案数・修正・権利範囲を確定 | F5: prices.ts / PROPOSED_PRICES。現金費0は上限確認用であり実原価ではない
A6: 取材記事 | B6: 55000 | C6: 0 | D6: =(B6*(1-前提!$B$3-前提!$B$4)-C6)/前提!$B$2 -> 5.17 | E6: 取材・文字起こし・執筆・確認を合算 | F6: prices.ts / PROPOSED_PRICES。現金費0は上限確認用であり実原価ではない
A7: LP | B7: 198000 | C7: 0 | D7: =(B7*(1-前提!$B$3-前提!$B$4)-C7)/前提!$B$2 -> 18.612 | E7: 18.61hが上限（現金費0）。原稿・確認を含め実測 | F7: prices.ts / PROPOSED_PRICES。現金費0は上限確認用であり実原価ではない
A8: 外部予約連携 | B8: 55000 | C8: 0 | D8: =(B8*(1-前提!$B$3-前提!$B$4)-C8)/前提!$B$2 -> 5.17 | E8: リンク設置とAPI開発を分離 | F8: prices.ts / PROPOSED_PRICES。現金費0は上限確認用であり実原価ではない
A9: 追加言語 | B9: 165000 | C9: 0 | D9: =(B9*(1-前提!$B$3-前提!$B$4)-C9)/前提!$B$2 -> 15.51 | E9: 準備中。翻訳と継続更新の費用は別 | F9: prices.ts / PROPOSED_PRICES。現金費0は上限確認用であり実原価ではない
A10: 個別CMS案 | B10: 598000 | C10: 0 | D10: =(B10*(1-前提!$B$3-前提!$B$4)-C10)/前提!$B$2 -> 56.212 | E10: 未採用。36hと現金費4万円の既存仮定では25%増にも対応 | F10: prices.ts / PROPOSED_PRICES。現金費0は上限確認用であり実原価ではない
A11: 独自機能案 | B11: 898000 | C11: 0 | D11: =(B11*(1-前提!$B$3-前提!$B$4)-C11)/前提!$B$2 -> 84.412 | E11: 未採用。50hと現金費5万円の仮定。運用責任は別 | F11: prices.ts / PROPOSED_PRICES。現金費0は上限確認用であり実原価ではない
A12: 設計案 | B12: 55000 | C12: 0 | D12: =(B12*(1-前提!$B$3-前提!$B$4)-C12)/前提!$B$2 -> 5.17 | E12: 未採用。開発受注時は総額の内訳。二重請求しない | F12: prices.ts / PROPOSED_PRICES。現金費0は上限確認用であり実原価ではない
A13: 技術保守案/月 | B13: 29800 | C13: 0 | D13: =(B13*(1-前提!$B$3-前提!$B$4)-C13)/前提!$B$2 -> 2.8012 | E13: 未採用。既存の育てるとは別商品。対応時間・現金原価未確定 | F13: prices.ts / PROPOSED_PRICES。現金費0は上限確認用であり実原価ではない

Sheet 月次構成
A1: ケース | B1: 土台件数 | C1: CMS件数 | D1: 守る社数 | E1: 整える社数 | F1: 育てる社数 | G1: 価格区分 | H1: 売上 | I1: 工数h | J1: 現金変動費 | K1: 全140h評価後余力 | L1: 25%増+支援30分h | M1: 84h以内 | N1: 注意
A2: 既存将来モデル | B2: 1 | C2: 1 | D2: 10 | E2: 16 | F2: 6 | G2: 現行 | H2: =B2*基本料金!C3+C2*基本料金!C4+D2*基本料金!C6+E2*基本料金!C7+F2*基本料金!C8 -> 970600 | I2: =B2*基本料金!D3+C2*基本料金!D4+D2*基本料金!D6+E2*基本料金!D7+F2*基本料金!D8 -> 69.5 | J2: =B2*基本料金!E3+C2*基本料金!E4+D2*基本料金!E6+E2*基本料金!E7+F2*基本料金!E8+H2*前提!$B$3 -> 87718 | K2: =H2-J2-前提!$B$8-前提!$B$5*前提!$B$2 -> 132882 | L2: =I2*前提!$B$9+SUM(D2:F2)*前提!$B$10 -> 102.875 | M2: =IF(L2<=前提!$B$5-前提!$B$6-前提!$B$7,"可","超過") -> 超過 | N2: CMS未提供・32社は仮定
A3: CMS除外 | B3: 1 | C3: 0 | D3: 10 | E3: 16 | F3: 6 | G3: 現行 | H3: =B3*基本料金!C3+C3*基本料金!C4+D3*基本料金!C6+E3*基本料金!C7+F3*基本料金!C8 -> 572600 | I3: =B3*基本料金!D3+C3*基本料金!D4+D3*基本料金!D6+E3*基本料金!D7+F3*基本料金!D8 -> 43.5 | J3: =B3*基本料金!E3+C3*基本料金!E4+D3*基本料金!E6+E3*基本料金!E7+F3*基本料金!E8+H3*前提!$B$3 -> 45778 | K3: =H3-J3-前提!$B$8-前提!$B$5*前提!$B$2 -> -223178 | L3: =I3*前提!$B$9+SUM(D3:F3)*前提!$B$10 -> 70.375 | M3: =IF(L3<=前提!$B$5-前提!$B$6-前提!$B$7,"可","超過") -> 可 | N3: 32社は仮定
A4: 土台2件 | B4: 2 | C4: 0 | D4: 10 | E4: 16 | F4: 6 | G4: 現行 | H4: =B4*基本料金!C3+C4*基本料金!C4+D4*基本料金!C6+E4*基本料金!C7+F4*基本料金!C8 -> 770600 | I4: =B4*基本料金!D3+C4*基本料金!D4+D4*基本料金!D6+E4*基本料金!D7+F4*基本料金!D8 -> 58.5 | J4: =B4*基本料金!E3+C4*基本料金!E4+D4*基本料金!E6+E4*基本料金!E7+F4*基本料金!E8+H4*前提!$B$3 -> 66718 | K4: =H4-J4-前提!$B$8-前提!$B$5*前提!$B$2 -> -46118 | L4: =I4*前提!$B$9+SUM(D4:F4)*前提!$B$10 -> 89.125 | M4: =IF(L4<=前提!$B$5-前提!$B$6-前提!$B$7,"可","超過") -> 超過 | N4: 32社は仮定
A5: 土台3件 | B5: 3 | C5: 0 | D5: 10 | E5: 16 | F5: 6 | G5: 現行 | H5: =B5*基本料金!C3+C5*基本料金!C4+D5*基本料金!C6+E5*基本料金!C7+F5*基本料金!C8 -> 968600 | I5: =B5*基本料金!D3+C5*基本料金!D4+D5*基本料金!D6+E5*基本料金!D7+F5*基本料金!D8 -> 73.5 | J5: =B5*基本料金!E3+C5*基本料金!E4+D5*基本料金!E6+E5*基本料金!E7+F5*基本料金!E8+H5*前提!$B$3 -> 87658 | K5: =H5-J5-前提!$B$8-前提!$B$5*前提!$B$2 -> 130942 | L5: =I5*前提!$B$9+SUM(D5:F5)*前提!$B$10 -> 107.875 | M5: =IF(L5<=前提!$B$5-前提!$B$6-前提!$B$7,"可","超過") -> 超過 | N5: 通常予約67.2h超過
A6: 改定検討 土台2件 | B6: 2 | C6: 0 | D6: 10 | E6: 16 | F6: 6 | G6: 検討 | H6: =B6*基本料金!I3+C6*基本料金!I4+D6*基本料金!I6+E6*基本料金!I7+F6*基本料金!I8 -> 978600 | I6: =B6*基本料金!J3+C6*基本料金!J4+D6*基本料金!J6+E6*基本料金!J7+F6*基本料金!J8 -> 75.375 | J6: =B6*基本料金!E3+C6*基本料金!E4+D6*基本料金!E6+E6*基本料金!E7+F6*基本料金!E8+H6*前提!$B$3 -> 72958 | K6: =H6-J6-前提!$B$8-前提!$B$5*前提!$B$2 -> 155642 | L6: =I6*前提!$B$9+SUM(D6:F6)*前提!$B$10 -> 110.21875 | M6: =IF(L6<=前提!$B$5-前提!$B$6-前提!$B$7,"可","超過") -> 超過 | N6: 新価格の需要は未確認。工数も増やした保守的入力
A7: 立上げ 土台1件のみ | B7: 1 | C7: 0 | D7: 0 | E7: 0 | F7: 0 | G7: 現行 | H7: =B7*基本料金!C3+C7*基本料金!C4+D7*基本料金!C6+E7*基本料金!C7+F7*基本料金!C8 -> 198000 | I7: =B7*基本料金!D3+C7*基本料金!D4+D7*基本料金!D6+E7*基本料金!D7+F7*基本料金!D8 -> 15 | J7: =B7*基本料金!E3+C7*基本料金!E4+D7*基本料金!E6+E7*基本料金!E7+F7*基本料金!E8+H7*前提!$B$3 -> 20940 | K7: =H7-J7-前提!$B$8-前提!$B$5*前提!$B$2 -> -572940 | L7: =I7*前提!$B$9+SUM(D7:F7)*前提!$B$10 -> 18.75 | M7: =IF(L7<=前提!$B$5-前提!$B$6-前提!$B$7,"可","超過") -> 可 | N7: 支援顧客なし

Sheet 顧客総額
A1: 制作 | B1: 支援 | C1: 現行制作 | D1: 現行支援/月 | E1: 検討制作 | F1: 検討支援/月 | G1: 外部費/月 | H1: 現行36か月 | I1: 検討36か月 | J1: 差 | K1: 注意
A2: 1ページ/自己管理 | B2: 5 | C2: =基本料金!C2 -> 79800 | D2: =基本料金!C5 -> 0 | E2: =基本料金!I2 -> 99800 | F2: =基本料金!I5 -> 0 | G2: =前提!B11 -> 3500 | H2: =C2+(D2+G2)*前提!$B$12 -> 205800 | I2: =E2+(F2+G2)*前提!$B$12 -> 225800 | J2: =I2-H2 -> 20000 | K2: 税別概算。CMS有料枠・オプションは別
A3: 6ページ/自己管理 | B3: 5 | C3: =基本料金!C3 -> 198000 | D3: =基本料金!C5 -> 0 | E3: =基本料金!I3 -> 248000 | F3: =基本料金!I5 -> 0 | G3: =前提!B11 -> 3500 | H3: =C3+(D3+G3)*前提!$B$12 -> 324000 | I3: =E3+(F3+G3)*前提!$B$12 -> 374000 | J3: =I3-H3 -> 50000 | K3: 税別概算。CMS有料枠・オプションは別
A4: 6ページ/整える | B4: 7 | C4: =基本料金!C3 -> 198000 | D4: =基本料金!C7 -> 9800 | E4: =基本料金!I3 -> 248000 | F4: =基本料金!I7 -> 12800 | G4: =前提!B11 -> 3500 | H4: =C4+(D4+G4)*前提!$B$12 -> 676800 | I4: =E4+(F4+G4)*前提!$B$12 -> 834800 | J4: =I4-H4 -> 158000 | K4: 税別概算。CMS有料枠・オプションは別
A5: CMS/自己管理 | B5: 5 | C5: =基本料金!C4 -> 398000 | D5: =基本料金!C5 -> 0 | E5: =基本料金!I4 -> 448000 | F5: =基本料金!I5 -> 0 | G5: =前提!B11 -> 3500 | H5: =C5+(D5+G5)*前提!$B$12 -> 524000 | I5: =E5+(F5+G5)*前提!$B$12 -> 574000 | J5: =I5-H5 -> 50000 | K5: 税別概算。CMS有料枠・オプションは別

Sheet 外部費と不足
A1: 費目 | B1: 確認内容 | C1: 判断 | D1: 公式情報/根拠
A2: Vercel Pro | B2: 20米ドル/月、追加席・従量・税に注意 | C2: 顧客直接契約は顧客負担。自社共有分と重複計上しない | D2: https://vercel.com/pricing
A3: 静的配信代替 | B3: Cloudflare静的資産へのリクエストと保存は無料 | C3: 移行未実施。DNS・ヘッダー・ログ・復元・責任範囲を検証してから | D3: https://developers.cloudflare.com/workers/static-assets/billing-and-limitations/
A4: microCMS | B4: Hobby 0円、Team 4900円〜/月 | C4: 追加メンバー・権限要件・従量・税の確認。CMS受付開始とは別 | D4: https://microcms.io/pricing
A5: さくら .com | B5: 更新表示3437円/年。請求時の税区分を確認 | C5: 取得年の価格ではなく更新を基準にする | D5: https://domain.sakura.ad.jp/specification/
A6: ムームー .com | B6: 更新表示1728円＋別途調整費。2026年9月26.25% | C6: 表示切替による二重加算に注意。請求画面で確定 | D6: https://muumuu-domain.com/domain/price
A7: AI/開発ツール | B7: 実請求未確認 | C7: 固定費5万円へ明細積算。案件実費と二重計上しない | D7: 実際の請求書が必要
A8: メール・フォーム・SMS | B8: 実請求/選定未確認 | C8: アドレス数・保存・送信数・通知先で見積 | D8: 顧客別構成が必要
A9: 外部バックアップ/監視 | B9: 独立保管と通知の費用未確定 | C9: 保守の300円/社と固定費への配賦を決める | D9: docs/operations.md
A10: 写真/翻訳/移行/法務確認 | B10: 単価・範囲未確認 | C10: 許諾・再撮影・移動・修正・検証を含め積算 | D10: 個別見積
A11: 決済/返金/未回収 | B11: 3%は保守的な仮定 | C11: 振込・カード等の実際の手段別に置換 | D11: proposal.json
A12: 補助金/掲載料削減 | B12: 売価値引きの確定財源ではない | C12: 未採択分・未確定削減額は基準収支から除く | D12: https://r6.jizokukahojokin.info/
