Workbook

Sheet 00 はじめに
A1: 紬｜全プラン比較・料金試算
A2: 2026-09-17 版 制作・月額・追加オプション・上位検討案を 1 冊に。現行価格の写しであり、このファイルを変えても公開料金は変わりません。
A5: プラン | B5: 区分 | C5: 状態 | D5: 税別（円） | E5: 税込（円） | F5: 要点
A6: ='01 制作プラン'!A6 -> 入口をつくる | B6: 制作／設計 | C6: ='01 制作プラン'!B6 -> 現行 | D6: ='01 制作プラン'!C6 -> 79800 | E6: ='01 制作プラン'!D6 -> 87780 | F6: 1 ページ・既存構成・支給素材
A7: ='01 制作プラン'!A7 -> 事業の土台をつくる | B7: 制作／設計 | C7: ='01 制作プラン'!B7 -> 現行 | D7: ='01 制作プラン'!C7 -> 198000 | E7: ='01 制作プラン'!D7 -> 217800 | F7: 最大 6 ページ・事業情報の整理
A8: ='01 制作プラン'!A8 -> 情報を育てる | B8: 制作／設計 | C8: ='01 制作プラン'!B8 -> 受付準備中 | D8: ='01 制作プラン'!C8 -> 398000 | E8: ='01 制作プラン'!D8 -> 437800 | F8: 最大 9 ページ・自己更新（準備中）
A9: ='01 制作プラン'!A9 -> 個別設計 CMS | B9: 制作／設計 | C9: ='01 制作プラン'!B9 -> 検討案・見積例 | D9: ='01 制作プラン'!C9 -> 598000 | E9: ='01 制作プラン'!D9 -> 657800 | F9: 個別設計が必要な CMS の見積例
A10: ='01 制作プラン'!A10 -> 独自の仕組みをつくる | B10: 制作／設計 | C10: ='01 制作プラン'!B10 -> 検討案・下限仮説 | D10: ='01 制作プラン'!C10 -> 898000 | E10: ='01 制作プラン'!D10 -> 987800 | F10: 単一業務の機能開発。設計費を含む
A11: ='01 制作プラン'!A11 -> 機能設計 | B11: 制作／設計 | C11: ='01 制作プラン'!B11 -> 検討案 | D11: ='01 制作プラン'!C11 -> 55000 | E11: ='01 制作プラン'!D11 -> 60500 | F11: 開発前の有料設計。条件付きで総額に充当
A13: ='02 月額サポート'!A6 -> 自分で管理 | B13: 月額 | C13: ='02 月額サポート'!B6 -> 現行 | D13: ='02 月額サポート'!C6 -> 0 | E13: ='02 月額サポート'!D6 -> 0 | F13: 紬への月額なし。外部費と管理は顧客負担
A14: ='02 月額サポート'!A7 -> 守る | B14: 月額 | C14: ='02 月額サポート'!B7 -> 現行 | D14: ='02 月額サポート'!C7 -> 3900 | E14: ='02 月額サポート'!D7 -> 4290 | F14: 保守のみ。通常変更なし
A15: ='02 月額サポート'!A8 -> 整える | B15: 月額 | C15: ='02 月額サポート'!B8 -> 現行 | D15: ='02 月額サポート'!C8 -> 9800 | E15: ='02 月額サポート'!D8 -> 10780 | F15: 月 30 分の変更＋保守
A16: ='02 月額サポート'!A9 -> 育てる | B16: 月額 | C16: ='02 月額サポート'!B9 -> 現行 | D16: ='02 月額サポート'!C9 -> 29800 | E16: ='02 月額サポート'!D9 -> 32780 | F16: 月 90 分の改善＋30 分の打合せ＋保守
A17: ='02 月額サポート'!A10 -> 技術保守（独自機能） | B17: 月額 | C17: ='02 月額サポート'!B10 -> 検討案・下限仮説 | D17: ='02 月額サポート'!C10 -> 29800 | E17: ='02 月額サポート'!D10 -> 32780 | F17: 独自機能向け。既存「育てる」とは別内容
A19: 読み方：現行＝現行料金定義／受付準備中＝提供検証前／検討案＝未採用。黄色・青文字は入力、黒文字は計算、緑文字は別シート参照。税別が基本で、0 円も省略せず表示。
A20: まず「01 制作」「02 月額」「03 追加」で内容を比較。「04 総額」で支払総額を試算。「05〜07」は経営検討用です。営業先への送付時は、未採用案と社内採算の扱いを確認してください。
A23: → 01 制作プラン | D23: 制作 6 項目（現行・準備中・検討案）
A24: → 02 月額サポート | D24: 月額 5 項目（現行・検討案）
A25: → 03 追加オプション | D25: 現行オプション 8 項目
A26: → 04 総額シミュレーター | D26: 入力例 6 ケース。プラン・月額・外部費を変更可
A27: → 05 月次採算 | D27: 10 ケースの採算と工数超過チェック
A28: → 06 受注構成 | D28: 月の受注件数・支援社数を編集
A29: → 07 計算前提 | D29: 税率・工数・原価・現金費の入力
A30: → 08 条件と出典 | D30: 販売条件と確認元

Sheet 01 制作プラン
A1: 制作プラン｜現行と検討案
A2: 税別／税込を併記。黄色セルは試算用入力。398,000 円の CMS は受付準備中。金額を編集してもサイトは変わりません。
A5: プラン | B5: 状態 | C5: 税別（円） | D5: 税込（円） | E5: 規模・方式 | F5: 含む内容 | G5: 含まない内容・境界 | H5: 期間・確認 | I5: 根拠
A6: 入口をつくる | B6: 現行 | C6: 79800 | D6: =ROUND(C6*(1+'07 計算前提'!$B$6),0) -> 87780 | E6: 最大 1 ページ React / TypeScript / Next.js を用いた制作 | F6: 顧客名義のドメイン・契約先の設定（実費別） スマートフォン対応・常時 SSL 30 分の聞き取りと支給素材からの原稿整理 支給写真の調整・配置 連絡先・既存予約先への導線 ソースコード一式の納品 | G6: 出張撮影・取材記事・新しい機能の開発 更新管理画面・月次の保守や変更作業 | H6: 2 週間目安 確認 1 回 | I6: [S1] 価格データ [S2] 公開文言
A7: 事業の土台をつくる | B7: 現行 | C7: 198000 | D7: =ROUND(C7*(1+'07 計算前提'!$B$6),0) -> 217800 | E7: 最大 6 ページ React / TypeScript / Next.js を用いた制作 | F7: 顧客名義のドメイン・契約先の設定（実費別） スマートフォン対応・常時 SSL 60 分の聞き取りと全ページの原稿整理 サービス・料金・信頼情報の構成設計 合意した納品仕様の検証レポート 問い合わせ導線の設定（受付先は提供確認後） ソースコード一式の納品 | G7: 撮影・ロゴ・独自機能等は別途。CMS の具体的な商品化条件は検討案を参照。 | H7: 4 週間目安 確認 2 回 | I7: [S1] 価格データ [S2] 公開文言
A8: 情報を育てる | B8: 受付準備中 | C8: 398000 | D8: =ROUND(C8*(1+'07 計算前提'!$B$6),0) -> 437800 | E8: 最大 9 ページ React / TypeScript / Next.js を用いた制作 | F8: 事業の土台をつくる内容を含む 更新管理画面（準備中） 最大 9 ページ・確認 2 回 記事・事例の標準テンプレート（準備中） 初期登録 3 件（支給素材から作成） 更新操作の説明 | G8: 撮影・ロゴ・独自機能等は別途。CMS の具体的な商品化条件は検討案を参照。 | H8: 6 週間目安 確認 2 回 | I8: [S1] 価格データ [S2] 公開文言
A9: 個別設計 CMS | B9: 検討案・見積例 | C9: 598000 | D9: =ROUND(C9*(1+'07 計算前提'!$B$6),0) -> 657800 | E9: 個別 CMS／36 時間仮定 | F9: 専用の情報設計・主要画面デザイン。公開サイト＋2 種の投稿。 | G9: 多言語・特殊移行・追加連携は別途。固定の第 4 商品にしない。 | H9: 個別見積もり | I9: [S3] 上位商品設計
A10: 独自の仕組みをつくる | B10: 検討案・下限仮説 | C10: 898000 | D10: =ROUND(C10*(1+'07 計算前提'!$B$6),0) -> 987800 | E10: 1 事業・1 業務／50 時間仮定 | F10: 条件検索・概算計算など、合意した単一業務の機能。設計 55,000 円分を含む。 | G10: 会員・決済・返金・複雑な権限・リアルタイム予約等は定型対象外。 | H10: 有料設計後に確定 | I10: [S3] 上位商品設計
A11: 機能設計 | B11: 検討案 | C11: 55000 | D11: =ROUND(C11*(1+'07 計算前提'!$B$6),0) -> 60500 | E11: 1 業務／合計 3 時間以内 | F11: 聞き取り、処理の図、代替手段の検討、完成条件、費用見積もり。 | G11: 実装・全画面の詳細デザインは含まない。実装発注の義務なし。 | H11: 同一設計で 60 日以内の開発契約なら総額に充当する案 | I11: [S3] 上位商品設計
A13: 398,000 円の検討範囲：共通構成・最大 9 種類の画面、投稿 2 種まで、初期登録 3 件、説明 60 分以内、確認 2 回、公開後確認 30 分。完全自由設計ではなく、提供検証後に受付開始。
A14: 既存の制作方式も React / TypeScript / Next.js。上位だけを「良いコード」とは扱わず、自己更新・固有機能・運用の違いで価格を分けます。ソース一式の引き継ぎは現行全プランの共通条件。

Sheet 02 月額サポート
A1: 月額サポート｜任意で選ぶ
A2: 自己管理は紬への月額 0 円。ドメイン・ホスティング・CMS 等の外部費は別途。作業枠と社内原価工数を混同しません。
A5: プラン | B5: 状態 | C5: 月額税別（円） | D5: 月額税込（円） | E5: 作業枠 | F5: 打合せ | G5: 含む内容 | H5: 対象外・条件
A6: 自分で管理 | B6: 現行 | C6: 0 | D6: =ROUND(C6*(1+'07 計算前提'!$B$6),0) -> 0 | E6: 通常の変更作業なし | F6: 定例会議なし | G6: 納品時の引継ぎ資料 月次監視・変更作業・継続相談は含みません | H6: 月次監視・変更・継続相談なし。顧客自身で運用。
A7: 守る | B7: 現行 | C7: 3900 | D7: =ROUND(C7*(1+'07 計算前提'!$B$6),0) -> 4290 | E7: 通常の変更作業なし | F7: 定例会議なし | G7: 定型監視・期限管理（外部サービス実費別） 週次バックアップの確認 障害時の一次切り分け（営業時間内） 通常の変更・投稿・会議は対象外 | H7: 外部費別途。通常変更は別依頼。
A8: 整える | B8: 現行 | C8: 9800 | D8: =ROUND(C8*(1+'07 計算前提'!$B$6),0) -> 10780 | E8: 30 分／月 | F8: 定例会議なし | G8: 「守る」の内容を含む 月 30 分の変更作業 作業履歴と使用時間の共有 枠を超える前に翌月対応か追加見積もりを選択 | H8: 1 か月単位。未使用枠の繰越なし。超過前に翌月対応または追加見積もり。
A9: 育てる | B9: 現行 | C9: 29800 | D9: =ROUND(C9*(1+'07 計算前提'!$B$6),0) -> 32780 | E9: 90 分／月 | F9: 30 分／月 | G9: 「守る」の内容を含む 月 90 分の改善作業 月 30 分の打合せ 施策 1 件の確認記録 作業枠を資料・フォーム・既存 SaaS 設定にも利用可 広告費・撮影・独自開発・記事の量産は対象外 | H9: 1 か月単位。未使用枠の繰越なし。超過前に翌月対応または追加見積もり。
A10: 技術保守（独自機能） | B10: 検討案・下限仮説 | C10: 29800 | D10: =ROUND(C10*(1+'07 計算前提'!$B$6),0) -> 32780 | E10: 合計 2 時間／月を仮定 | F10: 上記合計枠に含む案 | G10: 監視確認・定型の依存更新と検証・バックアップ確認等。 | H10: 既存「育てる」と内容は異なる。二重課金しない。緊急対応・大規模復旧・24 時間有人対応は別途設計。
A12: 通常の変更枠は「整える」30 分、「育てる」90 分。5 分単位で月の実作業を合算し、依頼ごとの切り上げや超過の自動課金は行いません。
A13: 支援終了を理由にサイトを削除しません。外部契約の継続と日々の運用は必要です。仕様不適合の修補を有料の変更作業に付け替えません。

Sheet 03 追加オプション
A1: 追加オプション｜現行の全 8 項目
A2: 金額は制作プランへの追加費用。撮影は参考額で、移動・編集・調整を含む総額を着手前に確定します。
A5: オプション | B5: 状態・価格区分 | C5: 税別（円） | D5: 税込（円） | E5: 対象・条件 | F5: 含まれない費用／注意 | G5: 出典
A6: ページ追加（既存構成にないもの） | B6: 現行・定額 | C6: 33000 | D6: =ROUND(C6*(1+'07 計算前提'!$B$6),0) -> 36300 | E6: 原稿・写真の聞き取り込み | F6: 成果物・回数・納期などの範囲は着手前に確定。 | G6: [S1/S2]
A7: 出張撮影 半日（別見積もり） | B7: 現行・別見積参考額 | C7: 55000 | D7: =ROUND(C7*(1+'07 計算前提'!$B$6),0) -> 60500 | E7: 移動・編集・調整を含め、着手前に総額を確定 | F7: 成果物・回数・納期などの範囲は着手前に確定。 | G7: [S1/S2]
A8: 出張撮影 1 日（別見積もり） | B8: 現行・別見積参考額 | C8: 88000 | D8: =ROUND(C8*(1+'07 計算前提'!$B$6),0) -> 96800 | E8: 移動・編集・調整を含め、着手前に総額を確定 | F8: 成果物・回数・納期などの範囲は着手前に確定。 | G8: [S1/S2]
A9: ロゴ制作（3 案・使用ルール付き） | B9: 現行・定額 | C9: 88000 | D9: =ROUND(C9*(1+'07 計算前提'!$B$6),0) -> 96800 | E9: 詳細は契約前に合意 | F9: 成果物・回数・納期などの範囲は着手前に確定。 | G9: [S1/S2]
A10: 記事の作成（取材あり） | B10: 現行・定額 | C10: 55000 | D10: =ROUND(C10*(1+'07 計算前提'!$B$6),0) -> 60500 | E10: 月次枠で完結しない記事制作は別見積もり | F10: 成果物・回数・納期などの範囲は着手前に確定。 | G10: [S1/S2]
A11: ランディングページ 1 枚 | B11: 現行・定額 | C11: 198000 | D11: =ROUND(C11*(1+'07 計算前提'!$B$6),0) -> 217800 | E11: キャンペーン・単一商品向け | F11: 成果物・回数・納期などの範囲は着手前に確定。 | G11: [S1/S2]
A12: 予約システムの連携 | B12: 現行・定額 | C12: 55000 | D12: =ROUND(C12*(1+'07 計算前提'!$B$6),0) -> 60500 | E12: 月額はお客様が直接ご契約（当方は設定費のみ） | F12: 外部予約サービスの月額は顧客直接契約。独自の予約機能開発ではありません。 | G12: [S1/S2]
A13: 多言語対応 1 言語（10 ページ以下） | B13: 現行・定額 | C13: 165000 | D13: =ROUND(C13*(1+'07 計算前提'!$B$6),0) -> 181500 | E13: 詳細は契約前に合意 | F13: 成果物・回数・納期などの範囲は着手前に確定。 | G13: [S1/S2]
A15: デザイン全面変更、他社サイトからの移管、新規の独自機能等は都度見積もり。未設定の料金を 0 円として扱いません。

Sheet 04 総額シミュレーター
A1: 総額シミュレーター｜保守なしも比較
A2: 例を入力済み。B〜E 列の黄色セルを変更すると総額が再計算されます。1 年・3 年は公開後の月数。外部費は顧客直接払いの概算。
A5: ケース | B5: 制作プラン | C5: 月額サポート | D5: 外部費／月 税別（円） | E5: 追加制作費 税別（円） | F5: 初期費 税別（円） | G5: 継続費／月 税別（円） | H5: 1 年総額 税別（円） | I5: 3 年総額 税別（円） | J5: 3 年総額 税込概算（円）
A6: 1 ページ・自己管理 | B6: 入口をつくる | C6: 自分で管理 | D6: ='07 計算前提'!B15 -> 3500 | E6: 0 | F6: =INDEX('01 制作プラン'!$C$6:$C$10,MATCH(B6,'01 制作プラン'!$A$6:$A$10,0))+E6 -> 79800 | G6: =INDEX('02 月額サポート'!$C$6:$C$10,MATCH(C6,'02 月額サポート'!$A$6:$A$10,0))+D6 -> 3500 | H6: =F6+G6*'07 計算前提'!$B$24 -> 121800 | I6: =F6+G6*'07 計算前提'!$B$24*3 -> 205800 | J6: =ROUND(I6*(1+'07 計算前提'!$B$6),0) -> 226380
A7: 土台・自己管理 | B7: 事業の土台をつくる | C7: 自分で管理 | D7: ='07 計算前提'!B15 -> 3500 | E7: 0 | F7: =INDEX('01 制作プラン'!$C$6:$C$10,MATCH(B7,'01 制作プラン'!$A$6:$A$10,0))+E7 -> 198000 | G7: =INDEX('02 月額サポート'!$C$6:$C$10,MATCH(C7,'02 月額サポート'!$A$6:$A$10,0))+D7 -> 3500 | H7: =F7+G7*'07 計算前提'!$B$24 -> 240000 | I7: =F7+G7*'07 計算前提'!$B$24*3 -> 324000 | J7: =ROUND(I7*(1+'07 計算前提'!$B$6),0) -> 356400
A8: CMS・無料 CMS 枠 | B8: 情報を育てる | C8: 自分で管理 | D8: ='07 計算前提'!B15 -> 3500 | E8: 0 | F8: =INDEX('01 制作プラン'!$C$6:$C$10,MATCH(B8,'01 制作プラン'!$A$6:$A$10,0))+E8 -> 398000 | G8: =INDEX('02 月額サポート'!$C$6:$C$10,MATCH(C8,'02 月額サポート'!$A$6:$A$10,0))+D8 -> 3500 | H8: =F8+G8*'07 計算前提'!$B$24 -> 440000 | I8: =F8+G8*'07 計算前提'!$B$24*3 -> 524000 | J8: =ROUND(I8*(1+'07 計算前提'!$B$6),0) -> 576400
A9: CMS・有料 CMS 枠 | B9: 情報を育てる | C9: 自分で管理 | D9: ='07 計算前提'!B15+'07 計算前提'!B16 -> 8400 | E9: 0 | F9: =INDEX('01 制作プラン'!$C$6:$C$10,MATCH(B9,'01 制作プラン'!$A$6:$A$10,0))+E9 -> 398000 | G9: =INDEX('02 月額サポート'!$C$6:$C$10,MATCH(C9,'02 月額サポート'!$A$6:$A$10,0))+D9 -> 8400 | H9: =F9+G9*'07 計算前提'!$B$24 -> 498800 | I9: =F9+G9*'07 計算前提'!$B$24*3 -> 700400 | J9: =ROUND(I9*(1+'07 計算前提'!$B$6),0) -> 770440
A10: 独自機能・自己管理 | B10: 独自の仕組みをつくる | C10: 自分で管理 | D10: ='07 計算前提'!B17 -> 10000 | E10: 0 | F10: =INDEX('01 制作プラン'!$C$6:$C$10,MATCH(B10,'01 制作プラン'!$A$6:$A$10,0))+E10 -> 898000 | G10: =INDEX('02 月額サポート'!$C$6:$C$10,MATCH(C10,'02 月額サポート'!$A$6:$A$10,0))+D10 -> 10000 | H10: =F10+G10*'07 計算前提'!$B$24 -> 1018000 | I10: =F10+G10*'07 計算前提'!$B$24*3 -> 1258000 | J10: =ROUND(I10*(1+'07 計算前提'!$B$6),0) -> 1383800
A11: 独自機能・技術保守 | B11: 独自の仕組みをつくる | C11: 技術保守（独自機能） | D11: ='07 計算前提'!B17 -> 10000 | E11: 0 | F11: =INDEX('01 制作プラン'!$C$6:$C$10,MATCH(B11,'01 制作プラン'!$A$6:$A$10,0))+E11 -> 898000 | G11: =INDEX('02 月額サポート'!$C$6:$C$10,MATCH(C11,'02 月額サポート'!$A$6:$A$10,0))+D11 -> 39800 | H11: =F11+G11*'07 計算前提'!$B$24 -> 1375600 | I11: =F11+G11*'07 計算前提'!$B$24*3 -> 2330800 | J11: =ROUND(I11*(1+'07 計算前提'!$B$6),0) -> 2563880
A13: 外部費に含める契約・為替・座席・従量を個別確認してください。税込欄は全費用へ同一税率を適用した概算で、海外請求等の実際の税処理を確定するものではありません。顧客の自己管理時間は表外。
A14: CMS・独自機能・技術保守には準備中／検討案が含まれます。組合せ選択は提供可否を保証しません。898,000 円の開発初期費には機能設計 55,000 円が含まれる案のため、E 列へ重ねて加算しません。

Sheet 05 月次採算
A1: 月次採算｜本人の全 140 時間も評価
A2: 受注構成・価格・前提を変えると再計算。余力は税引後利益ではありません。獲得費と決済費を含め、本人時間は全時間分を一度だけ控除。
A5: ケース | B5: 売上（円） | C5: うち月額（円） | D5: 制作・支援 時間 | E5: 現金変動費 決済費含む（円） | F5: 本人時間控除前 余力（円） | G5: 全時間控除後 余力（円） | H5: 25% 増の 時間 | I5: 複合ストレス 時間 | J5: 複合ストレス 判定
A6: ='06 受注構成'!A6 -> 土台 1 件のみ | B6: ='06 受注構成'!B6*'07 計算前提'!F28+'06 受注構成'!C6*'07 計算前提'!F29+'06 受注構成'!D6*'07 計算前提'!F30+'06 受注構成'!E6*'07 計算前提'!F31+'06 受注構成'!F6*'07 計算前提'!F32+'06 受注構成'!G6*'07 計算前提'!F33+'06 受注構成'!H6*'07 計算前提'!F34+'06 受注構成'!I6*'07 計算前提'!F35+'06 受注構成'!J6*'07 計算前提'!F39+'06 受注構成'!K6*'07 計算前提'!F40+'06 受注構成'!L6*'07 計算前提'!F41 -> 198000 | C6: ='06 受注構成'!J6*'07 計算前提'!F39+'06 受注構成'!K6*'07 計算前提'!F40+'06 受注構成'!L6*'07 計算前提'!F41 -> 0 | D6: ='06 受注構成'!B6*'07 計算前提'!H28+'06 受注構成'!C6*'07 計算前提'!H29+'06 受注構成'!D6*'07 計算前提'!H30+'06 受注構成'!E6*'07 計算前提'!H31+'06 受注構成'!F6*'07 計算前提'!H32+'06 受注構成'!G6*'07 計算前提'!H33+'06 受注構成'!H6*'07 計算前提'!H34+'06 受注構成'!I6*'07 計算前提'!H35+'06 受注構成'!J6*'07 計算前提'!H39+'06 受注構成'!K6*'07 計算前提'!H40+'06 受注構成'!L6*'07 計算前提'!H41 -> 15 | E6: ='06 受注構成'!B6*'07 計算前提'!G28+'06 受注構成'!C6*'07 計算前提'!G29+'06 受注構成'!D6*'07 計算前提'!G30+'06 受注構成'!E6*'07 計算前提'!G31+'06 受注構成'!F6*'07 計算前提'!G32+'06 受注構成'!G6*'07 計算前提'!G33+'06 受注構成'!H6*'07 計算前提'!G34+'06 受注構成'!I6*'07 計算前提'!G35+'06 受注構成'!J6*'07 計算前提'!G39+'06 受注構成'!K6*'07 計算前提'!G40+'06 受注構成'!L6*'07 計算前提'!G41+B6*'07 計算前提'!$B$12 -> 20940 | F6: =B6-E6-'07 計算前提'!$B$11 -> 127060 | G6: =F6-'07 計算前提'!$B$7*'07 計算前提'!$B$10 -> -572940 | H6: =D6*'07 計算前提'!$B$13 -> 18.75 | I6: =H6+SUM('06 受注構成'!J6:L6)*'07 計算前提'!$B$18 -> 18.75 | J6: =IF(I6<='07 計算前提'!$B$21,"容量内","容量超過") -> 容量内
A7: ='06 受注構成'!A7 -> 旧案 CMS 2 件・各 30 時間 | B7: ='06 受注構成'!B7*'07 計算前提'!F28+'06 受注構成'!C7*'07 計算前提'!F29+'06 受注構成'!D7*'07 計算前提'!F30+'06 受注構成'!E7*'07 計算前提'!F31+'06 受注構成'!F7*'07 計算前提'!F32+'06 受注構成'!G7*'07 計算前提'!F33+'06 受注構成'!H7*'07 計算前提'!F34+'06 受注構成'!I7*'07 計算前提'!F35+'06 受注構成'!J7*'07 計算前提'!F39+'06 受注構成'!K7*'07 計算前提'!F40+'06 受注構成'!L7*'07 計算前提'!F41 -> 796000 | C7: ='06 受注構成'!J7*'07 計算前提'!F39+'06 受注構成'!K7*'07 計算前提'!F40+'06 受注構成'!L7*'07 計算前提'!F41 -> 0 | D7: ='06 受注構成'!B7*'07 計算前提'!H28+'06 受注構成'!C7*'07 計算前提'!H29+'06 受注構成'!D7*'07 計算前提'!H30+'06 受注構成'!E7*'07 計算前提'!H31+'06 受注構成'!F7*'07 計算前提'!H32+'06 受注構成'!G7*'07 計算前提'!H33+'06 受注構成'!H7*'07 計算前提'!H34+'06 受注構成'!I7*'07 計算前提'!H35+'06 受注構成'!J7*'07 計算前提'!H39+'06 受注構成'!K7*'07 計算前提'!H40+'06 受注構成'!L7*'07 計算前提'!H41 -> 60 | E7: ='06 受注構成'!B7*'07 計算前提'!G28+'06 受注構成'!C7*'07 計算前提'!G29+'06 受注構成'!D7*'07 計算前提'!G30+'06 受注構成'!E7*'07 計算前提'!G31+'06 受注構成'!F7*'07 計算前提'!G32+'06 受注構成'!G7*'07 計算前提'!G33+'06 受注構成'!H7*'07 計算前提'!G34+'06 受注構成'!I7*'07 計算前提'!G35+'06 受注構成'!J7*'07 計算前提'!G39+'06 受注構成'!K7*'07 計算前提'!G40+'06 受注構成'!L7*'07 計算前提'!G41+B7*'07 計算前提'!$B$12 -> 83880 | F7: =B7-E7-'07 計算前提'!$B$11 -> 662120 | G7: =F7-'07 計算前提'!$B$7*'07 計算前提'!$B$10 -> -37880 | H7: =D7*'07 計算前提'!$B$13 -> 75 | I7: =H7+SUM('06 受注構成'!J7:L7)*'07 計算前提'!$B$18 -> 75 | J7: =IF(I7<='07 計算前提'!$B$21,"容量内","容量超過") -> 容量内
A8: ='06 受注構成'!A8 -> CMS 2 件・各 26 時間 | B8: ='06 受注構成'!B8*'07 計算前提'!F28+'06 受注構成'!C8*'07 計算前提'!F29+'06 受注構成'!D8*'07 計算前提'!F30+'06 受注構成'!E8*'07 計算前提'!F31+'06 受注構成'!F8*'07 計算前提'!F32+'06 受注構成'!G8*'07 計算前提'!F33+'06 受注構成'!H8*'07 計算前提'!F34+'06 受注構成'!I8*'07 計算前提'!F35+'06 受注構成'!J8*'07 計算前提'!F39+'06 受注構成'!K8*'07 計算前提'!F40+'06 受注構成'!L8*'07 計算前提'!F41 -> 796000 | C8: ='06 受注構成'!J8*'07 計算前提'!F39+'06 受注構成'!K8*'07 計算前提'!F40+'06 受注構成'!L8*'07 計算前提'!F41 -> 0 | D8: ='06 受注構成'!B8*'07 計算前提'!H28+'06 受注構成'!C8*'07 計算前提'!H29+'06 受注構成'!D8*'07 計算前提'!H30+'06 受注構成'!E8*'07 計算前提'!H31+'06 受注構成'!F8*'07 計算前提'!H32+'06 受注構成'!G8*'07 計算前提'!H33+'06 受注構成'!H8*'07 計算前提'!H34+'06 受注構成'!I8*'07 計算前提'!H35+'06 受注構成'!J8*'07 計算前提'!H39+'06 受注構成'!K8*'07 計算前提'!H40+'06 受注構成'!L8*'07 計算前提'!H41 -> 52 | E8: ='06 受注構成'!B8*'07 計算前提'!G28+'06 受注構成'!C8*'07 計算前提'!G29+'06 受注構成'!D8*'07 計算前提'!G30+'06 受注構成'!E8*'07 計算前提'!G31+'06 受注構成'!F8*'07 計算前提'!G32+'06 受注構成'!G8*'07 計算前提'!G33+'06 受注構成'!H8*'07 計算前提'!G34+'06 受注構成'!I8*'07 計算前提'!G35+'06 受注構成'!J8*'07 計算前提'!G39+'06 受注構成'!K8*'07 計算前提'!G40+'06 受注構成'!L8*'07 計算前提'!G41+B8*'07 計算前提'!$B$12 -> 83880 | F8: =B8-E8-'07 計算前提'!$B$11 -> 662120 | G8: =F8-'07 計算前提'!$B$7*'07 計算前提'!$B$10 -> -37880 | H8: =D8*'07 計算前提'!$B$13 -> 65 | I8: =H8+SUM('06 受注構成'!J8:L8)*'07 計算前提'!$B$18 -> 65 | J8: =IF(I8<='07 計算前提'!$B$21,"容量内","容量超過") -> 容量内
A9: ='06 受注構成'!A9 -> CMS 2 件＋土台 1 件 | B9: ='06 受注構成'!B9*'07 計算前提'!F28+'06 受注構成'!C9*'07 計算前提'!F29+'06 受注構成'!D9*'07 計算前提'!F30+'06 受注構成'!E9*'07 計算前提'!F31+'06 受注構成'!F9*'07 計算前提'!F32+'06 受注構成'!G9*'07 計算前提'!F33+'06 受注構成'!H9*'07 計算前提'!F34+'06 受注構成'!I9*'07 計算前提'!F35+'06 受注構成'!J9*'07 計算前提'!F39+'06 受注構成'!K9*'07 計算前提'!F40+'06 受注構成'!L9*'07 計算前提'!F41 -> 994000 | C9: ='06 受注構成'!J9*'07 計算前提'!F39+'06 受注構成'!K9*'07 計算前提'!F40+'06 受注構成'!L9*'07 計算前提'!F41 -> 0 | D9: ='06 受注構成'!B9*'07 計算前提'!H28+'06 受注構成'!C9*'07 計算前提'!H29+'06 受注構成'!D9*'07 計算前提'!H30+'06 受注構成'!E9*'07 計算前提'!H31+'06 受注構成'!F9*'07 計算前提'!H32+'06 受注構成'!G9*'07 計算前提'!H33+'06 受注構成'!H9*'07 計算前提'!H34+'06 受注構成'!I9*'07 計算前提'!H35+'06 受注構成'!J9*'07 計算前提'!H39+'06 受注構成'!K9*'07 計算前提'!H40+'06 受注構成'!L9*'07 計算前提'!H41 -> 67 | E9: ='06 受注構成'!B9*'07 計算前提'!G28+'06 受注構成'!C9*'07 計算前提'!G29+'06 受注構成'!D9*'07 計算前提'!G30+'06 受注構成'!E9*'07 計算前提'!G31+'06 受注構成'!F9*'07 計算前提'!G32+'06 受注構成'!G9*'07 計算前提'!G33+'06 受注構成'!H9*'07 計算前提'!G34+'06 受注構成'!I9*'07 計算前提'!G35+'06 受注構成'!J9*'07 計算前提'!G39+'06 受注構成'!K9*'07 計算前提'!G40+'06 受注構成'!L9*'07 計算前提'!G41+B9*'07 計算前提'!$B$12 -> 104820 | F9: =B9-E9-'07 計算前提'!$B$11 -> 839180 | G9: =F9-'07 計算前提'!$B$7*'07 計算前提'!$B$10 -> 139180 | H9: =D9*'07 計算前提'!$B$13 -> 83.75 | I9: =H9+SUM('06 受注構成'!J9:L9)*'07 計算前提'!$B$18 -> 83.75 | J9: =IF(I9<='07 計算前提'!$B$21,"容量内","容量超過") -> 容量内
A10: ='06 受注構成'!A10 -> CMS 2 件＋整える 10 社＋育てる 3 社 | B10: ='06 受注構成'!B10*'07 計算前提'!F28+'06 受注構成'!C10*'07 計算前提'!F29+'06 受注構成'!D10*'07 計算前提'!F30+'06 受注構成'!E10*'07 計算前提'!F31+'06 受注構成'!F10*'07 計算前提'!F32+'06 受注構成'!G10*'07 計算前提'!F33+'06 受注構成'!H10*'07 計算前提'!F34+'06 受注構成'!I10*'07 計算前提'!F35+'06 受注構成'!J10*'07 計算前提'!F39+'06 受注構成'!K10*'07 計算前提'!F40+'06 受注構成'!L10*'07 計算前提'!F41 -> 983400 | C10: ='06 受注構成'!J10*'07 計算前提'!F39+'06 受注構成'!K10*'07 計算前提'!F40+'06 受注構成'!L10*'07 計算前提'!F41 -> 187400 | D10: ='06 受注構成'!B10*'07 計算前提'!H28+'06 受注構成'!C10*'07 計算前提'!H29+'06 受注構成'!D10*'07 計算前提'!H30+'06 受注構成'!E10*'07 計算前提'!H31+'06 受注構成'!F10*'07 計算前提'!H32+'06 受注構成'!G10*'07 計算前提'!H33+'06 受注構成'!H10*'07 計算前提'!H34+'06 受注構成'!I10*'07 計算前提'!H35+'06 受注構成'!J10*'07 計算前提'!H39+'06 受注構成'!K10*'07 計算前提'!H40+'06 受注構成'!L10*'07 計算前提'!H41 -> 66.25 | E10: ='06 受注構成'!B10*'07 計算前提'!G28+'06 受注構成'!C10*'07 計算前提'!G29+'06 受注構成'!D10*'07 計算前提'!G30+'06 受注構成'!E10*'07 計算前提'!G31+'06 受注構成'!F10*'07 計算前提'!G32+'06 受注構成'!G10*'07 計算前提'!G33+'06 受注構成'!H10*'07 計算前提'!G34+'06 受注構成'!I10*'07 計算前提'!G35+'06 受注構成'!J10*'07 計算前提'!G39+'06 受注構成'!K10*'07 計算前提'!G40+'06 受注構成'!L10*'07 計算前提'!G41+B10*'07 計算前提'!$B$12 -> 95602 | F10: =B10-E10-'07 計算前提'!$B$11 -> 837798 | G10: =F10-'07 計算前提'!$B$7*'07 計算前提'!$B$10 -> 137798 | H10: =D10*'07 計算前提'!$B$13 -> 82.8125 | I10: =H10+SUM('06 受注構成'!J10:L10)*'07 計算前提'!$B$18 -> 89.3125 | J10: =IF(I10<='07 計算前提'!$B$21,"容量内","容量超過") -> 容量超過
A11: ='06 受注構成'!A11 -> 旧案開発 1 件＋土台 1 件 | B11: ='06 受注構成'!B11*'07 計算前提'!F28+'06 受注構成'!C11*'07 計算前提'!F29+'06 受注構成'!D11*'07 計算前提'!F30+'06 受注構成'!E11*'07 計算前提'!F31+'06 受注構成'!F11*'07 計算前提'!F32+'06 受注構成'!G11*'07 計算前提'!F33+'06 受注構成'!H11*'07 計算前提'!F34+'06 受注構成'!I11*'07 計算前提'!F35+'06 受注構成'!J11*'07 計算前提'!F39+'06 受注構成'!K11*'07 計算前提'!F40+'06 受注構成'!L11*'07 計算前提'!F41 -> 896000 | C11: ='06 受注構成'!J11*'07 計算前提'!F39+'06 受注構成'!K11*'07 計算前提'!F40+'06 受注構成'!L11*'07 計算前提'!F41 -> 0 | D11: ='06 受注構成'!B11*'07 計算前提'!H28+'06 受注構成'!C11*'07 計算前提'!H29+'06 受注構成'!D11*'07 計算前提'!H30+'06 受注構成'!E11*'07 計算前提'!H31+'06 受注構成'!F11*'07 計算前提'!H32+'06 受注構成'!G11*'07 計算前提'!H33+'06 受注構成'!H11*'07 計算前提'!H34+'06 受注構成'!I11*'07 計算前提'!H35+'06 受注構成'!J11*'07 計算前提'!H39+'06 受注構成'!K11*'07 計算前提'!H40+'06 受注構成'!L11*'07 計算前提'!H41 -> 65 | E11: ='06 受注構成'!B11*'07 計算前提'!G28+'06 受注構成'!C11*'07 計算前提'!G29+'06 受注構成'!D11*'07 計算前提'!G30+'06 受注構成'!E11*'07 計算前提'!G31+'06 受注構成'!F11*'07 計算前提'!G32+'06 受注構成'!G11*'07 計算前提'!G33+'06 受注構成'!H11*'07 計算前提'!G34+'06 受注構成'!I11*'07 計算前提'!G35+'06 受注構成'!J11*'07 計算前提'!G39+'06 受注構成'!K11*'07 計算前提'!G40+'06 受注構成'!L11*'07 計算前提'!G41+B11*'07 計算前提'!$B$12 -> 91880 | F11: =B11-E11-'07 計算前提'!$B$11 -> 754120 | G11: =F11-'07 計算前提'!$B$7*'07 計算前提'!$B$10 -> 54120 | H11: =D11*'07 計算前提'!$B$13 -> 81.25 | I11: =H11+SUM('06 受注構成'!J11:L11)*'07 計算前提'!$B$18 -> 81.25 | J11: =IF(I11<='07 計算前提'!$B$21,"容量内","容量超過") -> 容量内
A12: ='06 受注構成'!A12 -> 独自機能 1 件＋土台 1 件 | B12: ='06 受注構成'!B12*'07 計算前提'!F28+'06 受注構成'!C12*'07 計算前提'!F29+'06 受注構成'!D12*'07 計算前提'!F30+'06 受注構成'!E12*'07 計算前提'!F31+'06 受注構成'!F12*'07 計算前提'!F32+'06 受注構成'!G12*'07 計算前提'!F33+'06 受注構成'!H12*'07 計算前提'!F34+'06 受注構成'!I12*'07 計算前提'!F35+'06 受注構成'!J12*'07 計算前提'!F39+'06 受注構成'!K12*'07 計算前提'!F40+'06 受注構成'!L12*'07 計算前提'!F41 -> 1096000 | C12: ='06 受注構成'!J12*'07 計算前提'!F39+'06 受注構成'!K12*'07 計算前提'!F40+'06 受注構成'!L12*'07 計算前提'!F41 -> 0 | D12: ='06 受注構成'!B12*'07 計算前提'!H28+'06 受注構成'!C12*'07 計算前提'!H29+'06 受注構成'!D12*'07 計算前提'!H30+'06 受注構成'!E12*'07 計算前提'!H31+'06 受注構成'!F12*'07 計算前提'!H32+'06 受注構成'!G12*'07 計算前提'!H33+'06 受注構成'!H12*'07 計算前提'!H34+'06 受注構成'!I12*'07 計算前提'!H35+'06 受注構成'!J12*'07 計算前提'!H39+'06 受注構成'!K12*'07 計算前提'!H40+'06 受注構成'!L12*'07 計算前提'!H41 -> 65 | E12: ='06 受注構成'!B12*'07 計算前提'!G28+'06 受注構成'!C12*'07 計算前提'!G29+'06 受注構成'!D12*'07 計算前提'!G30+'06 受注構成'!E12*'07 計算前提'!G31+'06 受注構成'!F12*'07 計算前提'!G32+'06 受注構成'!G12*'07 計算前提'!G33+'06 受注構成'!H12*'07 計算前提'!G34+'06 受注構成'!I12*'07 計算前提'!G35+'06 受注構成'!J12*'07 計算前提'!G39+'06 受注構成'!K12*'07 計算前提'!G40+'06 受注構成'!L12*'07 計算前提'!G41+B12*'07 計算前提'!$B$12 -> 97880 | F12: =B12-E12-'07 計算前提'!$B$11 -> 948120 | G12: =F12-'07 計算前提'!$B$7*'07 計算前提'!$B$10 -> 248120 | H12: =D12*'07 計算前提'!$B$13 -> 81.25 | I12: =H12+SUM('06 受注構成'!J12:L12)*'07 計算前提'!$B$18 -> 81.25 | J12: =IF(I12<='07 計算前提'!$B$21,"容量内","容量超過") -> 容量内
A13: ='06 受注構成'!A13 -> 独自機能 1 件のみ | B13: ='06 受注構成'!B13*'07 計算前提'!F28+'06 受注構成'!C13*'07 計算前提'!F29+'06 受注構成'!D13*'07 計算前提'!F30+'06 受注構成'!E13*'07 計算前提'!F31+'06 受注構成'!F13*'07 計算前提'!F32+'06 受注構成'!G13*'07 計算前提'!F33+'06 受注構成'!H13*'07 計算前提'!F34+'06 受注構成'!I13*'07 計算前提'!F35+'06 受注構成'!J13*'07 計算前提'!F39+'06 受注構成'!K13*'07 計算前提'!F40+'06 受注構成'!L13*'07 計算前提'!F41 -> 898000 | C13: ='06 受注構成'!J13*'07 計算前提'!F39+'06 受注構成'!K13*'07 計算前提'!F40+'06 受注構成'!L13*'07 計算前提'!F41 -> 0 | D13: ='06 受注構成'!B13*'07 計算前提'!H28+'06 受注構成'!C13*'07 計算前提'!H29+'06 受注構成'!D13*'07 計算前提'!H30+'06 受注構成'!E13*'07 計算前提'!H31+'06 受注構成'!F13*'07 計算前提'!H32+'06 受注構成'!G13*'07 計算前提'!H33+'06 受注構成'!H13*'07 計算前提'!H34+'06 受注構成'!I13*'07 計算前提'!H35+'06 受注構成'!J13*'07 計算前提'!H39+'06 受注構成'!K13*'07 計算前提'!H40+'06 受注構成'!L13*'07 計算前提'!H41 -> 50 | E13: ='06 受注構成'!B13*'07 計算前提'!G28+'06 受注構成'!C13*'07 計算前提'!G29+'06 受注構成'!D13*'07 計算前提'!G30+'06 受注構成'!E13*'07 計算前提'!G31+'06 受注構成'!F13*'07 計算前提'!G32+'06 受注構成'!G13*'07 計算前提'!G33+'06 受注構成'!H13*'07 計算前提'!G34+'06 受注構成'!I13*'07 計算前提'!G35+'06 受注構成'!J13*'07 計算前提'!G39+'06 受注構成'!K13*'07 計算前提'!G40+'06 受注構成'!L13*'07 計算前提'!G41+B13*'07 計算前提'!$B$12 -> 76940 | F13: =B13-E13-'07 計算前提'!$B$11 -> 771060 | G13: =F13-'07 計算前提'!$B$7*'07 計算前提'!$B$10 -> 71060 | H13: =D13*'07 計算前提'!$B$13 -> 62.5 | I13: =H13+SUM('06 受注構成'!J13:L13)*'07 計算前提'!$B$18 -> 62.5 | J13: =IF(I13<='07 計算前提'!$B$21,"容量内","容量超過") -> 容量内
A14: ='06 受注構成'!A14 -> 入口 12 件 | B14: ='06 受注構成'!B14*'07 計算前提'!F28+'06 受注構成'!C14*'07 計算前提'!F29+'06 受注構成'!D14*'07 計算前提'!F30+'06 受注構成'!E14*'07 計算前提'!F31+'06 受注構成'!F14*'07 計算前提'!F32+'06 受注構成'!G14*'07 計算前提'!F33+'06 受注構成'!H14*'07 計算前提'!F34+'06 受注構成'!I14*'07 計算前提'!F35+'06 受注構成'!J14*'07 計算前提'!F39+'06 受注構成'!K14*'07 計算前提'!F40+'06 受注構成'!L14*'07 計算前提'!F41 -> 957600 | C14: ='06 受注構成'!J14*'07 計算前提'!F39+'06 受注構成'!K14*'07 計算前提'!F40+'06 受注構成'!L14*'07 計算前提'!F41 -> 0 | D14: ='06 受注構成'!B14*'07 計算前提'!H28+'06 受注構成'!C14*'07 計算前提'!H29+'06 受注構成'!D14*'07 計算前提'!H30+'06 受注構成'!E14*'07 計算前提'!H31+'06 受注構成'!F14*'07 計算前提'!H32+'06 受注構成'!G14*'07 計算前提'!H33+'06 受注構成'!H14*'07 計算前提'!H34+'06 受注構成'!I14*'07 計算前提'!H35+'06 受注構成'!J14*'07 計算前提'!H39+'06 受注構成'!K14*'07 計算前提'!H40+'06 受注構成'!L14*'07 計算前提'!H41 -> 66 | E14: ='06 受注構成'!B14*'07 計算前提'!G28+'06 受注構成'!C14*'07 計算前提'!G29+'06 受注構成'!D14*'07 計算前提'!G30+'06 受注構成'!E14*'07 計算前提'!G31+'06 受注構成'!F14*'07 計算前提'!G32+'06 受注構成'!G14*'07 計算前提'!G33+'06 受注構成'!H14*'07 計算前提'!G34+'06 受注構成'!I14*'07 計算前提'!G35+'06 受注構成'!J14*'07 計算前提'!G39+'06 受注構成'!K14*'07 計算前提'!G40+'06 受注構成'!L14*'07 計算前提'!G41+B14*'07 計算前提'!$B$12 -> 124728 | F14: =B14-E14-'07 計算前提'!$B$11 -> 782872 | G14: =F14-'07 計算前提'!$B$7*'07 計算前提'!$B$10 -> 82872 | H14: =D14*'07 計算前提'!$B$13 -> 82.5 | I14: =H14+SUM('06 受注構成'!J14:L14)*'07 計算前提'!$B$18 -> 82.5 | J14: =IF(I14<='07 計算前提'!$B$21,"容量内","容量超過") -> 容量内
A15: ='06 受注構成'!A15 -> 既存モデルの受注構成 | B15: ='06 受注構成'!B15*'07 計算前提'!F28+'06 受注構成'!C15*'07 計算前提'!F29+'06 受注構成'!D15*'07 計算前提'!F30+'06 受注構成'!E15*'07 計算前提'!F31+'06 受注構成'!F15*'07 計算前提'!F32+'06 受注構成'!G15*'07 計算前提'!F33+'06 受注構成'!H15*'07 計算前提'!F34+'06 受注構成'!I15*'07 計算前提'!F35+'06 受注構成'!J15*'07 計算前提'!F39+'06 受注構成'!K15*'07 計算前提'!F40+'06 受注構成'!L15*'07 計算前提'!F41 -> 970600 | C15: ='06 受注構成'!J15*'07 計算前提'!F39+'06 受注構成'!K15*'07 計算前提'!F40+'06 受注構成'!L15*'07 計算前提'!F41 -> 374600 | D15: ='06 受注構成'!B15*'07 計算前提'!H28+'06 受注構成'!C15*'07 計算前提'!H29+'06 受注構成'!D15*'07 計算前提'!H30+'06 受注構成'!E15*'07 計算前提'!H31+'06 受注構成'!F15*'07 計算前提'!H32+'06 受注構成'!G15*'07 計算前提'!H33+'06 受注構成'!H15*'07 計算前提'!H34+'06 受注構成'!I15*'07 計算前提'!H35+'06 受注構成'!J15*'07 計算前提'!H39+'06 受注構成'!K15*'07 計算前提'!H40+'06 受注構成'!L15*'07 計算前提'!H41 -> 69.5 | E15: ='06 受注構成'!B15*'07 計算前提'!G28+'06 受注構成'!C15*'07 計算前提'!G29+'06 受注構成'!D15*'07 計算前提'!G30+'06 受注構成'!E15*'07 計算前提'!G31+'06 受注構成'!F15*'07 計算前提'!G32+'06 受注構成'!G15*'07 計算前提'!G33+'06 受注構成'!H15*'07 計算前提'!G34+'06 受注構成'!I15*'07 計算前提'!G35+'06 受注構成'!J15*'07 計算前提'!G39+'06 受注構成'!K15*'07 計算前提'!G40+'06 受注構成'!L15*'07 計算前提'!G41+B15*'07 計算前提'!$B$12 -> 87718 | F15: =B15-E15-'07 計算前提'!$B$11 -> 832882 | G15: =F15-'07 計算前提'!$B$7*'07 計算前提'!$B$10 -> 132882 | H15: =D15*'07 計算前提'!$B$13 -> 86.875 | I15: =H15+SUM('06 受注構成'!J15:L15)*'07 計算前提'!$B$18 -> 102.875 | J15: =IF(I15<='07 計算前提'!$B$21,"容量内","容量超過") -> 容量超過
A17: 容量内でも受注できるとは限りません。営業・原稿待ち・検収遅延・月額解約・税・必要な生活費を別に確認。容量超過を外注で解消する追加費用は未計上です。旧案は比較用で販売プランではありません。

Sheet 06 受注構成
A1: 受注構成｜月の件数を編集
A2: 黄色セル＝月に売上計上する案件数・有料支援の契約社数。旧案は比較専用。ここは定常月の試算で、入金予定表ではありません。
A5: ケース | B5: 入口をつくる | C5: 事業の土台をつくる | D5: 標準 CMS（26 時間） | E5: 旧案 CMS（30 時間） | F5: 個別設計 CMS | G5: 旧案の独自機能（698,000 円） | H5: 独自の仕組みをつくる | I5: 機能設計のみ | J5: 守る（社） | K5: 整える（社） | L5: 育てる（社）
A6: 土台 1 件のみ | B6: 0 | C6: 1 | D6: 0 | E6: 0 | F6: 0 | G6: 0 | H6: 0 | I6: 0 | J6: 0 | K6: 0 | L6: 0
A7: 旧案 CMS 2 件・各 30 時間 | B7: 0 | C7: 0 | D7: 0 | E7: 2 | F7: 0 | G7: 0 | H7: 0 | I7: 0 | J7: 0 | K7: 0 | L7: 0
A8: CMS 2 件・各 26 時間 | B8: 0 | C8: 0 | D8: 2 | E8: 0 | F8: 0 | G8: 0 | H8: 0 | I8: 0 | J8: 0 | K8: 0 | L8: 0
A9: CMS 2 件＋土台 1 件 | B9: 0 | C9: 1 | D9: 2 | E9: 0 | F9: 0 | G9: 0 | H9: 0 | I9: 0 | J9: 0 | K9: 0 | L9: 0
A10: CMS 2 件＋整える 10 社＋育てる 3 社 | B10: 0 | C10: 0 | D10: 2 | E10: 0 | F10: 0 | G10: 0 | H10: 0 | I10: 0 | J10: 0 | K10: 10 | L10: 3
A11: 旧案開発 1 件＋土台 1 件 | B11: 0 | C11: 1 | D11: 0 | E11: 0 | F11: 0 | G11: 1 | H11: 0 | I11: 0 | J11: 0 | K11: 0 | L11: 0
A12: 独自機能 1 件＋土台 1 件 | B12: 0 | C12: 1 | D12: 0 | E12: 0 | F12: 0 | G12: 0 | H12: 1 | I12: 0 | J12: 0 | K12: 0 | L12: 0
A13: 独自機能 1 件のみ | B13: 0 | C13: 0 | D13: 0 | E13: 0 | F13: 0 | G13: 0 | H13: 1 | I13: 0 | J13: 0 | K13: 0 | L13: 0
A14: 入口 12 件 | B14: 12 | C14: 0 | D14: 0 | E14: 0 | F14: 0 | G14: 0 | H14: 0 | I14: 0 | J14: 0 | K14: 0 | L14: 0
A15: 既存モデルの受注構成 | B15: 0 | C15: 1 | D15: 1 | E15: 0 | F15: 0 | G15: 0 | H15: 0 | I15: 0 | J15: 10 | K15: 16 | L15: 6
A17: 開発価格には同じ案件の有料設計を含むため、同じ案件を「独自機能」と「機能設計のみ」に重複計上しないでください。「機能設計のみ」は開発へ進まなかった単独受注を想定。

Sheet 07 計算前提
A1: 計算前提｜試算用の入力を中央管理
A2: 青文字・黄色＝編集する仮定／黒＝計算式／緑＝別シート参照。実績ではありません。月 140 時間以外の経営値は既存モデル・検討案。
A5: 前提 | B5: 値 | C5: 単位 | D5: 根拠・解釈 | E5: 備考 | F5: 価格／月額 | G5: 現金変動費 | H5: 工数 | I5: 案件貢献額 | J5: 案件貢献率 | K5: 配賦による点検価格
A6: 税率 | B6: 0.1 | C6: 率 | D6: [S1] 料金表示の税率
A7: 月の全稼働時間 | B7: 140 | C7: 時間 | D7: ユーザー指定
A8: 営業・事務 | B8: 28 | C8: 時間／月 | D8: [S4] 既存の仮定
A9: 予備 | B9: 28 | C9: 時間／月 | D9: [S4] 既存の仮定
A10: 本人の時間原価 | B10: 5000 | C10: 円／時間 | D10: [S4] 機会費用の仮定。現金支出ではない
A11: 固定費 | B11: 50000 | C11: 円／月 | D11: [S4] 既存の仮定
A12: 決済費率 | B12: 0.03 | C12: 率 | D12: [S4] 保守的な試算用。銀行振込実績ではない
A13: 工数増の倍率 | B13: 1.25 | C13: 倍 | D13: [S3] 25% の工数超過ストレス
A14: 全体余力の目標率 | B14: 0.15 | C14: 率 | D14: [S3] 価格点検用の仮置き
A15: 外部費の標準概算 | B15: 3500 | C15: 円／月・税別 | D15: [S1] 顧客直接払い。固定料金の保証ではない
A16: 有料 CMS の追加概算 | B16: 4900 | C16: 円／月・税別 | D16: [S3] microCMS Team 参考・2026-09-17
A17: 独自機能の外部費概算 | B17: 10000 | C17: 円／月・税別 | D17: [S3] 未採用の計算用仮定
... A20: 設計費充当の期限 | B20: 60 | C20: 日 | D20: [S3] 同一設計の開発への充当案
A21: 制作・支援の契約可能枠 | B21: =B7-B8-B9 -> 84 | C21: 時間／月 | D21: 全時間から営業・事務と予備を控除
A22: 通常予約の上限 | B22: =IF(B13>0,B21/B13,0) -> 67.2 | C22: 時間／月 | D22: 工数増を契約枠内で吸収する目安
A23: 月の全時間・固定費原価 | B23: =B7*B10+B11 -> 750000 | C23: 円／月 | D23: 本人の全時間を一度だけ評価
A24: 1 年の月数 | B24: 12 | C24: か月 | D24: 総額の期間換算
A25: 通常予約 1 時間の配賦原価 | B25: =IF(B22>0,B23/B22,0) -> 11160.714 | C25: 円／時間 | D25: 点検用。月次採算では再度控除しない
A28: 入口をつくる | B28: 試算仮定 | C28: 制作 | D28: [S3/S4] 価格以外は未検証の工数・獲得費等 | F28: ='01 制作プラン'!C6 -> 79800 | G28: 8000 | H28: 5.5 | I28: =F28*(1-$B$12)-G28-H28*$B$10 -> 41906 | J28: =IF(F28>0,I28/F28,0) -> 0.52513784 | K28: =IF(1-$B$12-$B$14>0,(H28*$B$25+G28)/(1-$B$12-$B$14),0) -> 84614.547
A29: 事業の土台をつくる | B29: 試算仮定 | C29: 制作 | D29: [S3/S4] 価格以外は未検証の工数・獲得費等 | F29: ='01 制作プラン'!C7 -> 198000 | G29: 15000 | H29: 15 | I29: =F29*(1-$B$12)-G29-H29*$B$10 -> 102060 | J29: =IF(F29>0,I29/F29,0) -> 0.51545455 | K29: =IF(1-$B$12-$B$14>0,(H29*$B$25+G29)/(1-$B$12-$B$14),0) -> 222452.09
A30: 標準 CMS（26 時間） | B30: 試算仮定 | C30: 制作 | D30: [S3/S4] 価格以外は未検証の工数・獲得費等 | F30: ='01 制作プラン'!C8 -> 398000 | G30: 30000 | H30: 26 | I30: =F30*(1-$B$12)-G30-H30*$B$10 -> 226060 | J30: =IF(F30>0,I30/F30,0) -> 0.56798995 | K30: =IF(1-$B$12-$B$14>0,(H30*$B$25+G30)/(1-$B$12-$B$14),0) -> 390461.67
A31: 旧案 CMS（30 時間） | B31: 旧案・販売対象外 | C31: 制作 | D31: [S3/S4] 価格以外は未検証の工数・獲得費等 | F31: ='01 制作プラン'!C8 -> 398000 | G31: 30000 | H31: 30 | I31: =F31*(1-$B$12)-G31-H31*$B$10 -> 206060 | J31: =IF(F31>0,I31/F31,0) -> 0.51773869 | K31: =IF(1-$B$12-$B$14>0,(H31*$B$25+G31)/(1-$B$12-$B$14),0) -> 444904.18
A32: 個別設計 CMS | B32: 試算仮定 | C32: 制作 | D32: [S3/S4] 価格以外は未検証の工数・獲得費等 | F32: ='01 制作プラン'!C9 -> 598000 | G32: 40000 | H32: 36 | I32: =F32*(1-$B$12)-G32-H32*$B$10 -> 360060 | J32: =IF(F32>0,I32/F32,0) -> 0.60210702 | K32: =IF(1-$B$12-$B$14>0,(H32*$B$25+G32)/(1-$B$12-$B$14),0) -> 538763.07
A33: 旧案の独自機能（698,000 円） | B33: 旧案・販売対象外 | C33: 制作 | D33: [S3/S4] 価格以外は未検証の工数・獲得費等 | F33: 698000 | G33: 50000 | H33: 50 | I33: =F33*(1-$B$12)-G33-H33*$B$10 -> 377060 | J33: =IF(F33>0,I33/F33,0) -> 0.54020057 | K33: =IF(1-$B$12-$B$14>0,(H33*$B$25+G33)/(1-$B$12-$B$14),0) -> 741506.97
A34: 独自の仕組みをつくる | B34: 試算仮定 | C34: 制作 | D34: [S3/S4] 価格以外は未検証の工数・獲得費等 | E34: 設計は開発総額に含む | F34: ='01 制作プラン'!C10 -> 898000 | G34: 50000 | H34: 50 | I34: =F34*(1-$B$12)-G34-H34*$B$10 -> 571060 | J34: =IF(F34>0,I34/F34,0) -> 0.63592428 | K34: =IF(1-$B$12-$B$14>0,(H34*$B$25+G34)/(1-$B$12-$B$14),0) -> 741506.97
A35: 機能設計のみ | B35: 試算仮定 | C35: 制作 | D35: [S3/S4] 価格以外は未検証の工数・獲得費等 | F35: ='01 制作プラン'!C11 -> 55000 | G35: 2000 | H35: 3 | I35: =F35*(1-$B$12)-G35-H35*$B$10 -> 36350 | J35: =IF(F35>0,I35/F35,0) -> 0.66090909 | K35: =IF(1-$B$12-$B$14>0,(H35*$B$25+G35)/(1-$B$12-$B$14),0) -> 43270.906
A38: 自分で管理 | B38: 既存モデルの仮定 | C38: 月額 | D38: [S4] 社内の確認・連絡時間を含む | E38: 顧客の作業枠とは異なる | F38: ='02 月額サポート'!C6 -> 0 | G38: 0 | H38: 0 | I38: =F38*(1-$B$12)-G38-H38*$B$10 -> 0 | J38: =IF(F38>0,I38/F38,0) -> 0
A39: 守る | B39: 既存モデルの仮定 | C39: 月額 | D39: [S4] 社内の確認・連絡時間を含む | E39: 顧客の作業枠とは異なる | F39: ='02 月額サポート'!C7 -> 3900 | G39: 300 | H39: 0.3 | I39: =F39*(1-$B$12)-G39-H39*$B$10 -> 1983 | J39: =IF(F39>0,I39/F39,0) -> 0.50846154
A40: 整える | B40: 既存モデルの仮定 | C40: 月額 | D40: [S4] 社内の確認・連絡時間を含む | E40: 顧客の作業枠とは異なる | F40: ='02 月額サポート'!C8 -> 9800 | G40: 400 | H40: 0.75 | I40: =F40*(1-$B$12)-G40-H40*$B$10 -> 5356 | J40: =IF(F40>0,I40/F40,0) -> 0.54653061
A41: 育てる | B41: 既存モデルの仮定 | C41: 月額 | D41: [S4] 社内の確認・連絡時間を含む | E41: 顧客の作業枠とは異なる | F41: ='02 月額サポート'!C9 -> 29800 | G41: 700 | H41: 2.25 | I41: =F41*(1-$B$12)-G41-H41*$B$10 -> 16956 | J41: =IF(F41>0,I41/F41,0) -> 0.56899329
A43: 技術保守 29,800 円は新規の検討案です。「育てる」と同一商品ではないため、月次採算の既存 10 ケースには混ぜていません。独自機能と機能設計を同じ案件として二重に受注計上しないでください。

Sheet 08 条件と出典
A1: 条件と出典｜販売状態と費用を混同しない
A2: この Excel は比較・検討用の写し。価格の正本は src/content/prices.ts。原典の更新時には写しの再確認が必要です。
A5: 区分 | B5: 項目 | C5: 内容 | D5: 参照・URL
A6: 基本 | B6: 公開と受付 | C6: 現行＝現在の料金定義。CMS＝価格設定済み・受付準備中。個別 CMS／独自機能／機能設計／技術保守＝未採用の検討案。 | D6: [S1][S3]
A7: 基本 | B7: 支払 | C7: 現行制作は着手 50%・検収 50%。独自開発案は総額 898,000 円のうち設計 55,000 円、着手時 394,000 円、検収時 449,000 円。追加請求ではなく内訳。 | D7: [S1][S3]
A8: 基本 | B8: 所有・継続 | C8: ソース一式を納品。顧客名義のドメイン・契約を基本とし、外部サービスの実費は別。支援終了後も顧客または引継ぎ先の運用が必要。 | D8: [S1][S2][S3]
A9: 基本 | B9: 変更の範囲 | C9: 変更枠は「整える」月 30 分、「育てる」月 90 分。5 分単位で月の実作業を合算し、依頼ごとに切り上げません。未使用枠は繰り越しません。超過前に翌月対応か追加見積もりを選んでいただき、自動で追加請求しません。 | D9: [S1][S2]
A10: 基本 | B10: 共通の品質 | C10: 価格差は機能・運用範囲で分ける。上位だけに安全性や良いコードを付けるものではない。測っていない効果や順位は保証しない。 | D10: [S3]
A11: 検討案 | B11: CMS の提供条件 | C11: 投稿→公開、下書き非公開、失敗通知、キー保護、バックアップ・復元、顧客による実操作、引き継ぎを検証してから受付開始。 | D11: [S3]
A12: 検討案 | B12: 保守なし | C12: 紬への継続支払 0 円の選択肢は維持。外部費・日々の管理・必要な技術対応が不要になる意味ではない。 | D12: [S1][S3]
A13: 経営 | B13: 価格と受注 | C13: 598,000 / 898,000 円等は採算からの仮説。市場の支払意思・実工数・受注率は未検証。旧案 698,000 円は採算比較のみ。 | D13: [S3]
A14: 出典 S1 | B14: 現行価格の正本 | C14: 制作 3・月額 4・追加オプション 8。抽出日 2026-09-17。税率・支払割合・外部費概算も含む。 | D14: src/content/prices.ts
A15: 出典 S2 | B15: 現行の提供範囲 | C15: プラン名、含む内容、対象外、変更枠の運用ルール。 | D15: src/i18n/locales/ja/prices.ts
A16: 出典 S3 | B16: 上位商品設計・検討案 | C16: 2026-09-17 の未採用案。市場調査・顧客価値・商品化計画・根拠 URL を含む。 | D16: docs/business/premium-pricing-proposal.md
... A20: 外部費 | B20: ドメイン等 | C20: ドメイン更新、CMS、ホスティング、予約等は顧客直接払い。契約先の料金・更新価格を確認し、総額シミュレーター D 列へ必要分を含める。 | D20: 外部サービスの個別契約により確定
